quantlet_strats/__init__.py
quantlet_strats/_version.py
quantlet_strats/bands.py
quantlet_strats/curves/__init__.py
quantlet_strats/curves/momentum.py
quantlet_strats/curves/portfolio.py
quantlet_strats/filter.py
quantlet_strats/mathfin.py
quantlet_strats/plot.py
quantlet_strats/rw.py
quantlet_strats/stats.py
quantlet.strats-0.0.2.dist-info/LICENSE
quantlet.strats-0.0.2.dist-info/WHEEL
quantlet.strats-0.0.2.dist-info/METADATA
quantlet.strats-0.0.2.dist-info/RECORD
