Metadata-Version: 2.1
Name: quantlet.strats
Version: 0.0.2
Summary: QuantLET-strats - QuantLET strategies, statistics, curves, filters, and financial engineering functions
Home-page: https://gitlab.com/jfaleiro/quantlet-strats
License: AGPL-3.0-or-later
Author: J Faleiro
Author-email: j@falei.ro
Requires-Python: >=3.8,<4.0
Classifier: Development Status :: 4 - Beta
Classifier: Intended Audience :: Developers
Classifier: License :: OSI Approved :: GNU Affero General Public License v3
Classifier: License :: OSI Approved :: GNU Affero General Public License v3 or later (AGPLv3+)
Classifier: Operating System :: OS Independent
Classifier: Programming Language :: Python
Classifier: Programming Language :: Python :: 3
Classifier: Programming Language :: Python :: 3.8
Classifier: Programming Language :: Python :: 3.9
Classifier: Topic :: Software Development
Classifier: Topic :: Software Development :: Libraries :: Python Modules
Provides-Extra: coverage
Provides-Extra: interactive-dev
Provides-Extra: tests
Requires-Dist: PyHamcrest; extra == "tests" or extra == "coverage"
Requires-Dist: autopep8 (>=1.5.5,<2.0.0); extra == "interactive-dev"
Requires-Dist: coverage (>=5.4,<6.0); extra == "coverage"
Requires-Dist: flake8 (>=3.8.4,<4.0.0); extra == "interactive-dev"
Requires-Dist: isort (>=5.7.0,<6.0.0); extra == "interactive-dev"
Requires-Dist: matplotlib (>=3.3.4,<4.0.0)
Requires-Dist: pre-commit (>=2.10.1,<3.0.0); extra == "interactive-dev"
Requires-Dist: pylint (>=2.7.0,<3.0.0)
Requires-Dist: pytest (>=6.2.2,<7.0.0); extra == "tests" or extra == "coverage"
Requires-Dist: quantlet.streaming (>=1.0.0,<2.0.0)
Requires-Dist: rope (>=0.18.0,<0.19.0); extra == "interactive-dev"
Requires-Dist: scipy (>=1.6.1,<2.0.0)
Requires-Dist: seaborn (>=0.11.1,<0.12.0)
Requires-Dist: statsmodels (>=0.12.2,<0.13.0)
